[
  {
    "id": "mock-24",
    "title": "Lesung mit Saša Stanišić",
    "author": "Saša Stanišić",
    "date": "2026-03-22T06:28:49.814Z",
    "location": {
      "name": "Stadtbibliothek Berlin",
      "address": "Musterstraße 74, Berlin",
      "lat": 52.50980299703852,
      "lng": 13.403691785992203
    },
    "price": {
      "amount": 18,
      "currency": "EUR"
    },
    "description": "Erleben Sie Saša Stanišić live in Berlin. Eine spannende Lesung aus dem neuesten Werk.",
    "url": "https://example.com",
    "source": "Mock Generator"
  },
  {
    "id": "mock-14",
    "title": "Lesung mit Sebastian Fitzek",
    "author": "Sebastian Fitzek",
    "date": "2026-03-24T21:43:54.023Z",
    "location": {
      "name": "Kulturhaus Stuttgart",
      "address": "Musterstraße 55, Stuttgart",
      "lat": 48.77716640048313,
      "lng": 9.201952953169773
    },
    "price": {
      "amount": 27,
      "currency": "EUR"
    },
    "description": "Erleben Sie Sebastian Fitzek live in Stuttgart. Eine spannende Lesung aus dem neuesten Werk.",
    "url": "https://example.com",
    "source": "Mock Generator"
  },
  {
    "id": "mock-33",
    "title": "Lesung mit Herta Müller",
    "author": "Herta Müller",
    "date": "2026-03-25T09:09:31.366Z",
    "location": {
      "name": "Thalia Buchhandlung Stuttgart",
      "address": "Musterstraße 38, Stuttgart",
      "lat": 48.7628110429936,
      "lng": 9.191733585911297
    },
    "price": {
      "amount": 32,
      "currency": "EUR"
    },
    "description": "Erleben Sie Herta Müller live in Stuttgart. Eine spannende Lesung aus dem neuesten Werk.",
    "url": "https://example.com",
    "source": "Mock Generator"
  },
  {
    "id": "mock-11",
    "title": "Lesung mit Juli Zeh",
    "author": "Juli Zeh",
    "date": "2026-03-25T21:52:02.716Z",
    "location": {
      "name": "Kulturhaus Dresden",
      "address": "Musterstraße 67, Dresden",
      "lat": 51.03390650169884,
      "lng": 13.734582154228992
    },
    "price": {
      "amount": 9,
      "currency": "EUR"
    },
    "description": "Erleben Sie Juli Zeh live in Dresden. Eine spannende Lesung aus dem neuesten Werk.",
    "url": "https://example.com",
    "source": "Mock Generator"
  },
  {
    "id": "mock-21",
    "title": "Lesung mit Cornelia Funke",
    "author": "Cornelia Funke",
    "date": "2026-03-27T13:06:50.596Z",
    "location": {
      "name": "Literaturhaus Leipzig",
      "address": "Musterstraße 96, Leipzig",
      "lat": 51.33429185550176,
      "lng": 12.362730720423102
    },
    "price": {
      "amount": 20,
      "currency": "EUR"
    },
    "description": "Erleben Sie Cornelia Funke live in Leipzig. Eine spannende Lesung aus dem neuesten Werk.",
    "url": "https://example.com",
    "source": "Mock Generator"
  },
  {
    "id": "mock-2",
    "title": "Lesung mit Marc-Uwe Kling",
    "author": "Marc-Uwe Kling",
    "date": "2026-03-27T13:28:32.867Z",
    "location": {
      "name": "Thalia Buchhandlung Berlin",
      "address": "Musterstraße 42, Berlin",
      "lat": 52.50897615283749,
      "lng": 13.415837207731519
    },
    "price": {
      "amount": 21,
      "currency": "EUR"
    },
    "description": "Erleben Sie Marc-Uwe Kling live in Berlin. Eine spannende Lesung aus dem neuesten Werk.",
    "url": "https://example.com",
    "source": "Mock Generator"
  },
  {
    "id": "mock-5",
    "title": "Lesung mit Ferdinand von Schirach",
    "author": "Ferdinand von Schirach",
    "date": "2026-03-28T01:47:33.913Z",
    "location": {
      "name": "Kulturhaus Leipzig",
      "address": "Musterstraße 29, Leipzig",
      "lat": 51.35703499306034,
      "lng": 12.37794547111068
    },
    "price": {
      "amount": 20,
      "currency": "EUR"
    },
    "description": "Erleben Sie Ferdinand von Schirach live in Leipzig. Eine spannende Lesung aus dem neuesten Werk.",
    "url": "https://example.com",
    "source": "Mock Generator"
  },
  {
    "id": "mock-19",
    "title": "Lesung mit Sebastian Fitzek",
    "author": "Sebastian Fitzek",
    "date": "2026-04-02T00:07:56.690Z",
    "location": {
      "name": "Thalia Buchhandlung Hamburg",
      "address": "Musterstraße 64, Hamburg",
      "lat": 53.555967087791316,
      "lng": 9.993570405771333
    },
    "price": {
      "amount": 28,
      "currency": "EUR"
    },
    "description": "Erleben Sie Sebastian Fitzek live in Hamburg. Eine spannende Lesung aus dem neuesten Werk.",
    "url": "https://example.com",
    "source": "Mock Generator"
  },
  {
    "id": "mock-43",
    "title": "Lesung mit Sebastian Fitzek",
    "author": "Sebastian Fitzek",
    "date": "2026-04-02T19:32:56.896Z",
    "location": {
      "name": "Volkshochschule Stuttgart",
      "address": "Musterstraße 84, Stuttgart",
      "lat": 48.75714798953086,
      "lng": 9.160519779038276
    },
    "price": {
      "amount": 27,
      "currency": "EUR"
    },
    "description": "Erleben Sie Sebastian Fitzek live in Stuttgart. Eine spannende Lesung aus dem neuesten Werk.",
    "url": "https://example.com",
    "source": "Mock Generator"
  },
  {
    "id": "mock-46",
    "title": "Lesung mit Marc-Uwe Kling",
    "author": "Marc-Uwe Kling",
    "date": "2026-04-04T23:03:59.531Z",
    "location": {
      "name": "Thalia Buchhandlung Berlin",
      "address": "Musterstraße 75, Berlin",
      "lat": 52.500541176344775,
      "lng": 13.427553853199763
    },
    "price": {
      "amount": 5,
      "currency": "EUR"
    },
    "description": "Erleben Sie Marc-Uwe Kling live in Berlin. Eine spannende Lesung aus dem neuesten Werk.",
    "url": "https://example.com",
    "source": "Mock Generator"
  },
  {
    "id": "mock-34",
    "title": "Lesung mit Herta Müller",
    "author": "Herta Müller",
    "date": "2026-04-07T03:01:20.593Z",
    "location": {
      "name": "Volkshochschule Hamburg",
      "address": "Musterstraße 48, Hamburg",
      "lat": 53.546002511051945,
      "lng": 9.969322818421041
    },
    "price": {
      "amount": 22,
      "currency": "EUR"
    },
    "description": "Erleben Sie Herta Müller live in Hamburg. Eine spannende Lesung aus dem neuesten Werk.",
    "url": "https://example.com",
    "source": "Mock Generator"
  },
  {
    "id": "mock-37",
    "title": "Lesung mit Ferdinand von Schirach",
    "author": "Ferdinand von Schirach",
    "date": "2026-04-07T03:47:31.651Z",
    "location": {
      "name": "Stadtbibliothek Frankfurt",
      "address": "Musterstraße 60, Frankfurt",
      "lat": 50.09740446331767,
      "lng": 8.694255851968919
    },
    "price": {
      "amount": 16,
      "currency": "EUR"
    },
    "description": "Erleben Sie Ferdinand von Schirach live in Frankfurt. Eine spannende Lesung aus dem neuesten Werk.",
    "url": "https://example.com",
    "source": "Mock Generator"
  },
  {
    "id": "mock-6",
    "title": "Lesung mit Saša Stanišić",
    "author": "Saša Stanišić",
    "date": "2026-04-09T00:13:22.368Z",
    "location": {
      "name": "Literaturhaus Köln",
      "address": "Musterstraße 57, Köln",
      "lat": 50.9545670376982,
      "lng": 6.959711916939579
    },
    "price": {
      "amount": 11,
      "currency": "EUR"
    },
    "description": "Erleben Sie Saša Stanišić live in Köln. Eine spannende Lesung aus dem neuesten Werk.",
    "url": "https://example.com",
    "source": "Mock Generator"
  },
  {
    "id": "mock-18",
    "title": "Lesung mit Daniel Kehlmann",
    "author": "Daniel Kehlmann",
    "date": "2026-04-15T17:45:09.393Z",
    "location": {
      "name": "Kulturhaus Stuttgart",
      "address": "Musterstraße 34, Stuttgart",
      "lat": 48.789582013962765,
      "lng": 9.175402402667968
    },
    "price": {
      "amount": 6,
      "currency": "EUR"
    },
    "description": "Erleben Sie Daniel Kehlmann live in Stuttgart. Eine spannende Lesung aus dem neuesten Werk.",
    "url": "https://example.com",
    "source": "Mock Generator"
  },
  {
    "id": "mock-36",
    "title": "Lesung mit Herta Müller",
    "author": "Herta Müller",
    "date": "2026-04-16T10:20:56.514Z",
    "location": {
      "name": "Kulturhaus München",
      "address": "Musterstraße 16, München",
      "lat": 48.117505856074345,
      "lng": 11.58664548018725
    },
    "price": {
      "amount": 34,
      "currency": "EUR"
    },
    "description": "Erleben Sie Herta Müller live in München. Eine spannende Lesung aus dem neuesten Werk.",
    "url": "https://example.com",
    "source": "Mock Generator"
  },
  {
    "id": "mock-41",
    "title": "Lesung mit Herta Müller",
    "author": "Herta Müller",
    "date": "2026-04-20T21:04:50.047Z",
    "location": {
      "name": "Kulturhaus Köln",
      "address": "Musterstraße 3, Köln",
      "lat": 50.93126360633491,
      "lng": 6.939972694517633
    },
    "price": {
      "amount": 8,
      "currency": "EUR"
    },
    "description": "Erleben Sie Herta Müller live in Köln. Eine spannende Lesung aus dem neuesten Werk.",
    "url": "https://example.com",
    "source": "Mock Generator"
  },
  {
    "id": "mock-12",
    "title": "Lesung mit Ferdinand von Schirach",
    "author": "Ferdinand von Schirach",
    "date": "2026-04-25T12:05:54.706Z",
    "location": {
      "name": "Kulturhaus Berlin",
      "address": "Musterstraße 35, Berlin",
      "lat": 52.52225214052492,
      "lng": 13.419217777454785
    },
    "price": {
      "amount": 34,
      "currency": "EUR"
    },
    "description": "Erleben Sie Ferdinand von Schirach live in Berlin. Eine spannende Lesung aus dem neuesten Werk.",
    "url": "https://example.com",
    "source": "Mock Generator"
  },
  {
    "id": "mock-15",
    "title": "Lesung mit Sebastian Fitzek",
    "author": "Sebastian Fitzek",
    "date": "2026-04-30T21:49:32.482Z",
    "location": {
      "name": "Volkshochschule Hamburg",
      "address": "Musterstraße 31, Hamburg",
      "lat": 53.537180598120585,
      "lng": 9.980649961075958
    },
    "price": {
      "amount": 27,
      "currency": "EUR"
    },
    "description": "Erleben Sie Sebastian Fitzek live in Hamburg. Eine spannende Lesung aus dem neuesten Werk.",
    "url": "https://example.com",
    "source": "Mock Generator"
  },
  {
    "id": "mock-8",
    "title": "Lesung mit Ferdinand von Schirach",
    "author": "Ferdinand von Schirach",
    "date": "2026-05-03T00:40:14.364Z",
    "location": {
      "name": "Literaturhaus Stuttgart",
      "address": "Musterstraße 0, Stuttgart",
      "lat": 48.77160814999933,
      "lng": 9.190040096743152
    },
    "price": {
      "amount": 19,
      "currency": "EUR"
    },
    "description": "Erleben Sie Ferdinand von Schirach live in Stuttgart. Eine spannende Lesung aus dem neuesten Werk.",
    "url": "https://example.com",
    "source": "Mock Generator"
  },
  {
    "id": "mock-1",
    "title": "Lesung mit Herta Müller",
    "author": "Herta Müller",
    "date": "2026-05-05T07:36:42.984Z",
    "location": {
      "name": "Literaturhaus Dresden",
      "address": "Musterstraße 25, Dresden",
      "lat": 51.041603422487356,
      "lng": 13.74630659143743
    },
    "price": {
      "amount": 29,
      "currency": "EUR"
    },
    "description": "Erleben Sie Herta Müller live in Dresden. Eine spannende Lesung aus dem neuesten Werk.",
    "url": "https://example.com",
    "source": "Mock Generator"
  },
  {
    "id": "mock-42",
    "title": "Lesung mit Marc-Uwe Kling",
    "author": "Marc-Uwe Kling",
    "date": "2026-05-05T14:01:28.454Z",
    "location": {
      "name": "Volkshochschule Dresden",
      "address": "Musterstraße 70, Dresden",
      "lat": 51.06776769829149,
      "lng": 13.71697596054407
    },
    "price": {
      "amount": 13,
      "currency": "EUR"
    },
    "description": "Erleben Sie Marc-Uwe Kling live in Dresden. Eine spannende Lesung aus dem neuesten Werk.",
    "url": "https://example.com",
    "source": "Mock Generator"
  },
  {
    "id": "mock-4",
    "title": "Lesung mit Herta Müller",
    "author": "Herta Müller",
    "date": "2026-05-08T03:11:05.262Z",
    "location": {
      "name": "Stadtbibliothek Hamburg",
      "address": "Musterstraße 97, Hamburg",
      "lat": 53.53802365841302,
      "lng": 10.008336748474822
    },
    "price": {
      "amount": 21,
      "currency": "EUR"
    },
    "description": "Erleben Sie Herta Müller live in Hamburg. Eine spannende Lesung aus dem neuesten Werk.",
    "url": "https://example.com",
    "source": "Mock Generator"
  },
  {
    "id": "mock-16",
    "title": "Lesung mit Sebastian Fitzek",
    "author": "Sebastian Fitzek",
    "date": "2026-05-08T09:52:19.136Z",
    "location": {
      "name": "Stadtbibliothek Frankfurt",
      "address": "Musterstraße 59, Frankfurt",
      "lat": 50.130898484159204,
      "lng": 8.683654998743839
    },
    "price": {
      "amount": 27,
      "currency": "EUR"
    },
    "description": "Erleben Sie Sebastian Fitzek live in Frankfurt. Eine spannende Lesung aus dem neuesten Werk.",
    "url": "https://example.com",
    "source": "Mock Generator"
  },
  {
    "id": "mock-9",
    "title": "Lesung mit Ferdinand von Schirach",
    "author": "Ferdinand von Schirach",
    "date": "2026-05-09T13:27:26.916Z",
    "location": {
      "name": "Stadtbibliothek Köln",
      "address": "Musterstraße 70, Köln",
      "lat": 50.94268866258476,
      "lng": 6.9486580026850335
    },
    "price": {
      "amount": 7,
      "currency": "EUR"
    },
    "description": "Erleben Sie Ferdinand von Schirach live in Köln. Eine spannende Lesung aus dem neuesten Werk.",
    "url": "https://example.com",
    "source": "Mock Generator"
  },
  {
    "id": "mock-38",
    "title": "Lesung mit Sebastian Fitzek",
    "author": "Sebastian Fitzek",
    "date": "2026-05-09T15:07:42.655Z",
    "location": {
      "name": "Thalia Buchhandlung Berlin",
      "address": "Musterstraße 4, Berlin",
      "lat": 52.504328318106865,
      "lng": 13.412190201898706
    },
    "price": {
      "amount": 18,
      "currency": "EUR"
    },
    "description": "Erleben Sie Sebastian Fitzek live in Berlin. Eine spannende Lesung aus dem neuesten Werk.",
    "url": "https://example.com",
    "source": "Mock Generator"
  },
  {
    "id": "mock-29",
    "title": "Lesung mit Saša Stanišić",
    "author": "Saša Stanišić",
    "date": "2026-05-09T16:40:15.280Z",
    "location": {
      "name": "Literaturhaus München",
      "address": "Musterstraße 73, München",
      "lat": 48.11865286843357,
      "lng": 11.59233452238858
    },
    "price": {
      "amount": 21,
      "currency": "EUR"
    },
    "description": "Erleben Sie Saša Stanišić live in München. Eine spannende Lesung aus dem neuesten Werk.",
    "url": "https://example.com",
    "source": "Mock Generator"
  },
  {
    "id": "mock-45",
    "title": "Lesung mit Ferdinand von Schirach",
    "author": "Ferdinand von Schirach",
    "date": "2026-05-15T08:04:29.965Z",
    "location": {
      "name": "Literaturhaus Frankfurt",
      "address": "Musterstraße 47, Frankfurt",
      "lat": 50.11488444920055,
      "lng": 8.672861491475958
    },
    "price": {
      "amount": 31,
      "currency": "EUR"
    },
    "description": "Erleben Sie Ferdinand von Schirach live in Frankfurt. Eine spannende Lesung aus dem neuesten Werk.",
    "url": "https://example.com",
    "source": "Mock Generator"
  },
  {
    "id": "mock-7",
    "title": "Lesung mit Sebastian Fitzek",
    "author": "Sebastian Fitzek",
    "date": "2026-05-16T23:47:42.692Z",
    "location": {
      "name": "Volkshochschule Köln",
      "address": "Musterstraße 6, Köln",
      "lat": 50.91570809414594,
      "lng": 6.9781539466753015
    },
    "price": {
      "amount": 26,
      "currency": "EUR"
    },
    "description": "Erleben Sie Sebastian Fitzek live in Köln. Eine spannende Lesung aus dem neuesten Werk.",
    "url": "https://example.com",
    "source": "Mock Generator"
  },
  {
    "id": "mock-32",
    "title": "Lesung mit Ferdinand von Schirach",
    "author": "Ferdinand von Schirach",
    "date": "2026-05-17T04:38:59.105Z",
    "location": {
      "name": "Thalia Buchhandlung Leipzig",
      "address": "Musterstraße 1, Leipzig",
      "lat": 51.355234610429996,
      "lng": 12.38608106569464
    },
    "price": {
      "amount": 23,
      "currency": "EUR"
    },
    "description": "Erleben Sie Ferdinand von Schirach live in Leipzig. Eine spannende Lesung aus dem neuesten Werk.",
    "url": "https://example.com",
    "source": "Mock Generator"
  },
  {
    "id": "mock-10",
    "title": "Lesung mit Ferdinand von Schirach",
    "author": "Ferdinand von Schirach",
    "date": "2026-05-19T16:30:38.072Z",
    "location": {
      "name": "Thalia Buchhandlung Köln",
      "address": "Musterstraße 65, Köln",
      "lat": 50.93079030490745,
      "lng": 6.938393131926361
    },
    "price": {
      "amount": 17,
      "currency": "EUR"
    },
    "description": "Erleben Sie Ferdinand von Schirach live in Köln. Eine spannende Lesung aus dem neuesten Werk.",
    "url": "https://example.com",
    "source": "Mock Generator"
  },
  {
    "id": "mock-30",
    "title": "Lesung mit Herta Müller",
    "author": "Herta Müller",
    "date": "2026-05-20T22:17:35.294Z",
    "location": {
      "name": "Literaturhaus Stuttgart",
      "address": "Musterstraße 46, Stuttgart",
      "lat": 48.79505909241648,
      "lng": 9.194767320364395
    },
    "price": {
      "amount": 13,
      "currency": "EUR"
    },
    "description": "Erleben Sie Herta Müller live in Stuttgart. Eine spannende Lesung aus dem neuesten Werk.",
    "url": "https://example.com",
    "source": "Mock Generator"
  },
  {
    "id": "mock-39",
    "title": "Lesung mit Cornelia Funke",
    "author": "Cornelia Funke",
    "date": "2026-05-23T02:03:24.242Z",
    "location": {
      "name": "Stadtbibliothek Leipzig",
      "address": "Musterstraße 19, Leipzig",
      "lat": 51.35248257238207,
      "lng": 12.379817612307045
    },
    "price": {
      "amount": 9,
      "currency": "EUR"
    },
    "description": "Erleben Sie Cornelia Funke live in Leipzig. Eine spannende Lesung aus dem neuesten Werk.",
    "url": "https://example.com",
    "source": "Mock Generator"
  },
  {
    "id": "mock-31",
    "title": "Lesung mit Herta Müller",
    "author": "Herta Müller",
    "date": "2026-05-23T22:06:13.340Z",
    "location": {
      "name": "Kulturhaus München",
      "address": "Musterstraße 53, München",
      "lat": 48.14601380776702,
      "lng": 11.585109051695953
    },
    "price": {
      "amount": 9,
      "currency": "EUR"
    },
    "description": "Erleben Sie Herta Müller live in München. Eine spannende Lesung aus dem neuesten Werk.",
    "url": "https://example.com",
    "source": "Mock Generator"
  },
  {
    "id": "mock-47",
    "title": "Lesung mit Cornelia Funke",
    "author": "Cornelia Funke",
    "date": "2026-05-28T15:07:41.550Z",
    "location": {
      "name": "Thalia Buchhandlung Berlin",
      "address": "Musterstraße 17, Berlin",
      "lat": 52.50275357620923,
      "lng": 13.419739428859364
    },
    "price": {
      "amount": 27,
      "currency": "EUR"
    },
    "description": "Erleben Sie Cornelia Funke live in Berlin. Eine spannende Lesung aus dem neuesten Werk.",
    "url": "https://example.com",
    "source": "Mock Generator"
  },
  {
    "id": "mock-0",
    "title": "Lesung mit Sebastian Fitzek",
    "author": "Sebastian Fitzek",
    "date": "2026-05-29T00:02:29.198Z",
    "location": {
      "name": "Literaturhaus Leipzig",
      "address": "Musterstraße 3, Leipzig",
      "lat": 51.360399156313534,
      "lng": 12.377654490637404
    },
    "price": {
      "amount": 21,
      "currency": "EUR"
    },
    "description": "Erleben Sie Sebastian Fitzek live in Leipzig. Eine spannende Lesung aus dem neuesten Werk.",
    "url": "https://example.com",
    "source": "Mock Generator"
  },
  {
    "id": "mock-49",
    "title": "Lesung mit Cornelia Funke",
    "author": "Cornelia Funke",
    "date": "2026-05-29T01:05:07.083Z",
    "location": {
      "name": "Stadtbibliothek Hamburg",
      "address": "Musterstraße 63, Hamburg",
      "lat": 53.57306433400971,
      "lng": 9.999709706469405
    },
    "price": {
      "amount": 8,
      "currency": "EUR"
    },
    "description": "Erleben Sie Cornelia Funke live in Hamburg. Eine spannende Lesung aus dem neuesten Werk.",
    "url": "https://example.com",
    "source": "Mock Generator"
  },
  {
    "id": "mock-48",
    "title": "Lesung mit Marc-Uwe Kling",
    "author": "Marc-Uwe Kling",
    "date": "2026-06-01T11:40:16.965Z",
    "location": {
      "name": "Volkshochschule Frankfurt",
      "address": "Musterstraße 91, Frankfurt",
      "lat": 50.09722856405363,
      "lng": 8.695550581785184
    },
    "price": {
      "amount": 8,
      "currency": "EUR"
    },
    "description": "Erleben Sie Marc-Uwe Kling live in Frankfurt. Eine spannende Lesung aus dem neuesten Werk.",
    "url": "https://example.com",
    "source": "Mock Generator"
  },
  {
    "id": "mock-17",
    "title": "Lesung mit Ferdinand von Schirach",
    "author": "Ferdinand von Schirach",
    "date": "2026-06-01T17:32:25.629Z",
    "location": {
      "name": "Kulturhaus Dresden",
      "address": "Musterstraße 54, Dresden",
      "lat": 51.04541957633435,
      "lng": 13.750122537659319
    },
    "price": {
      "amount": 18,
      "currency": "EUR"
    },
    "description": "Erleben Sie Ferdinand von Schirach live in Dresden. Eine spannende Lesung aus dem neuesten Werk.",
    "url": "https://example.com",
    "source": "Mock Generator"
  },
  {
    "id": "mock-44",
    "title": "Lesung mit Herta Müller",
    "author": "Herta Müller",
    "date": "2026-06-01T20:53:21.096Z",
    "location": {
      "name": "Stadtbibliothek Frankfurt",
      "address": "Musterstraße 38, Frankfurt",
      "lat": 50.10779785026279,
      "lng": 8.661939131041777
    },
    "price": {
      "amount": 15,
      "currency": "EUR"
    },
    "description": "Erleben Sie Herta Müller live in Frankfurt. Eine spannende Lesung aus dem neuesten Werk.",
    "url": "https://example.com",
    "source": "Mock Generator"
  },
  {
    "id": "mock-26",
    "title": "Lesung mit Herta Müller",
    "author": "Herta Müller",
    "date": "2026-06-03T03:24:48.084Z",
    "location": {
      "name": "Volkshochschule München",
      "address": "Musterstraße 67, München",
      "lat": 48.12128984263185,
      "lng": 11.571548871505714
    },
    "price": {
      "amount": 7,
      "currency": "EUR"
    },
    "description": "Erleben Sie Herta Müller live in München. Eine spannende Lesung aus dem neuesten Werk.",
    "url": "https://example.com",
    "source": "Mock Generator"
  },
  {
    "id": "mock-13",
    "title": "Lesung mit Sebastian Fitzek",
    "author": "Sebastian Fitzek",
    "date": "2026-06-04T03:39:33.689Z",
    "location": {
      "name": "Kulturhaus Dresden",
      "address": "Musterstraße 81, Dresden",
      "lat": 51.05132716806849,
      "lng": 13.739618158087266
    },
    "price": {
      "amount": 11,
      "currency": "EUR"
    },
    "description": "Erleben Sie Sebastian Fitzek live in Dresden. Eine spannende Lesung aus dem neuesten Werk.",
    "url": "https://example.com",
    "source": "Mock Generator"
  },
  {
    "id": "mock-35",
    "title": "Lesung mit Juli Zeh",
    "author": "Juli Zeh",
    "date": "2026-06-04T14:44:02.876Z",
    "location": {
      "name": "Stadtbibliothek Berlin",
      "address": "Musterstraße 11, Berlin",
      "lat": 52.51185319066563,
      "lng": 13.405728605787028
    },
    "price": {
      "amount": 14,
      "currency": "EUR"
    },
    "description": "Erleben Sie Juli Zeh live in Berlin. Eine spannende Lesung aus dem neuesten Werk.",
    "url": "https://example.com",
    "source": "Mock Generator"
  },
  {
    "id": "mock-27",
    "title": "Lesung mit Cornelia Funke",
    "author": "Cornelia Funke",
    "date": "2026-06-07T19:41:12.052Z",
    "location": {
      "name": "Stadtbibliothek Stuttgart",
      "address": "Musterstraße 62, Stuttgart",
      "lat": 48.7662899506837,
      "lng": 9.18418233336425
    },
    "price": {
      "amount": 33,
      "currency": "EUR"
    },
    "description": "Erleben Sie Cornelia Funke live in Stuttgart. Eine spannende Lesung aus dem neuesten Werk.",
    "url": "https://example.com",
    "source": "Mock Generator"
  },
  {
    "id": "mock-40",
    "title": "Lesung mit Sebastian Fitzek",
    "author": "Sebastian Fitzek",
    "date": "2026-06-08T13:42:26.042Z",
    "location": {
      "name": "Literaturhaus Frankfurt",
      "address": "Musterstraße 42, Frankfurt",
      "lat": 50.12410126652934,
      "lng": 8.703060026454049
    },
    "price": {
      "amount": 26,
      "currency": "EUR"
    },
    "description": "Erleben Sie Sebastian Fitzek live in Frankfurt. Eine spannende Lesung aus dem neuesten Werk.",
    "url": "https://example.com",
    "source": "Mock Generator"
  },
  {
    "id": "mock-20",
    "title": "Lesung mit Marc-Uwe Kling",
    "author": "Marc-Uwe Kling",
    "date": "2026-06-13T16:09:49.405Z",
    "location": {
      "name": "Volkshochschule Hamburg",
      "address": "Musterstraße 14, Hamburg",
      "lat": 53.55612852923325,
      "lng": 10.005123908790926
    },
    "price": {
      "amount": 5,
      "currency": "EUR"
    },
    "description": "Erleben Sie Marc-Uwe Kling live in Hamburg. Eine spannende Lesung aus dem neuesten Werk.",
    "url": "https://example.com",
    "source": "Mock Generator"
  },
  {
    "id": "mock-28",
    "title": "Lesung mit Saša Stanišić",
    "author": "Saša Stanišić",
    "date": "2026-06-13T19:42:54.005Z",
    "location": {
      "name": "Literaturhaus Köln",
      "address": "Musterstraße 16, Köln",
      "lat": 50.940706932066846,
      "lng": 6.980584627012294
    },
    "price": {
      "amount": 32,
      "currency": "EUR"
    },
    "description": "Erleben Sie Saša Stanišić live in Köln. Eine spannende Lesung aus dem neuesten Werk.",
    "url": "https://example.com",
    "source": "Mock Generator"
  },
  {
    "id": "mock-23",
    "title": "Lesung mit Juli Zeh",
    "author": "Juli Zeh",
    "date": "2026-06-13T23:01:54.581Z",
    "location": {
      "name": "Kulturhaus Stuttgart",
      "address": "Musterstraße 28, Stuttgart",
      "lat": 48.79039711081361,
      "lng": 9.196210857873961
    },
    "price": {
      "amount": 19,
      "currency": "EUR"
    },
    "description": "Erleben Sie Juli Zeh live in Stuttgart. Eine spannende Lesung aus dem neuesten Werk.",
    "url": "https://example.com",
    "source": "Mock Generator"
  },
  {
    "id": "mock-25",
    "title": "Lesung mit Daniel Kehlmann",
    "author": "Daniel Kehlmann",
    "date": "2026-06-13T23:18:54.011Z",
    "location": {
      "name": "Kulturhaus Köln",
      "address": "Musterstraße 93, Köln",
      "lat": 50.91863209857167,
      "lng": 6.9571678170868125
    },
    "price": {
      "amount": 34,
      "currency": "EUR"
    },
    "description": "Erleben Sie Daniel Kehlmann live in Köln. Eine spannende Lesung aus dem neuesten Werk.",
    "url": "https://example.com",
    "source": "Mock Generator"
  },
  {
    "id": "mock-3",
    "title": "Lesung mit Marc-Uwe Kling",
    "author": "Marc-Uwe Kling",
    "date": "2026-06-16T11:53:41.154Z",
    "location": {
      "name": "Volkshochschule München",
      "address": "Musterstraße 82, München",
      "lat": 48.12541509744888,
      "lng": 11.591186506624092
    },
    "price": {
      "amount": 9,
      "currency": "EUR"
    },
    "description": "Erleben Sie Marc-Uwe Kling live in München. Eine spannende Lesung aus dem neuesten Werk.",
    "url": "https://example.com",
    "source": "Mock Generator"
  },
  {
    "id": "mock-22",
    "title": "Lesung mit Marc-Uwe Kling",
    "author": "Marc-Uwe Kling",
    "date": "2026-06-20T02:07:42.358Z",
    "location": {
      "name": "Literaturhaus Stuttgart",
      "address": "Musterstraße 6, Stuttgart",
      "lat": 48.75903500068282,
      "lng": 9.194539751089565
    },
    "price": {
      "amount": 27,
      "currency": "EUR"
    },
    "description": "Erleben Sie Marc-Uwe Kling live in Stuttgart. Eine spannende Lesung aus dem neuesten Werk.",
    "url": "https://example.com",
    "source": "Mock Generator"
  }
]